afancontrol/__init__.py
afancontrol/__main__.py
afancontrol/arduino.py
afancontrol/config.py
afancontrol/configparser.py
afancontrol/daemon.py
afancontrol/exec.py
afancontrol/fans.py
afancontrol/fantest.py
afancontrol/filters.py
afancontrol/logger.py
afancontrol/manager.py
afancontrol/metrics.py
afancontrol/pwmfannorm.py
afancontrol/report.py
afancontrol/temps.py
afancontrol/trigger.py
afancontrol/pwmfan/__init__.py
afancontrol/pwmfan/arduino.py
afancontrol/pwmfan/base.py
afancontrol/pwmfan/ipmi.py
afancontrol/pwmfan/linux.py
afancontrol/temp/__init__.py
afancontrol/temp/base.py
afancontrol/temp/command.py
afancontrol/temp/file.py
afancontrol/temp/hdd.py
afancontrol-3.1.0.data/data/etc/afancontrol/afancontrol.conf
afancontrol-3.1.0.data/data/etc/systemd/system/afancontrol.service
afancontrol-3.1.0.dist-info/LICENSE
afancontrol-3.1.0.dist-info/METADATA
afancontrol-3.1.0.dist-info/WHEEL
afancontrol-3.1.0.dist-info/entry_points.txt
afancontrol-3.1.0.dist-info/top_level.txt
afancontrol-3.1.0.dist-info/RECORD
